README.md
setup.py
intron_retention_utils/__init__.py
intron_retention_utils/allele_count.py
intron_retention_utils/associate.py
intron_retention_utils/filter.py
intron_retention_utils/intron_db.py
intron_retention_utils/logger.py
intron_retention_utils/mutation.py
intron_retention_utils/my_seq.py
intron_retention_utils/parser.py
intron_retention_utils/pyssw.py
intron_retention_utils/run.py
intron_retention_utils/simple_count.py
intron_retention_utils/ssw_lib.py
intron_retention_utils/version.py
intron_retention_utils.egg-info/PKG-INFO
intron_retention_utils.egg-info/SOURCES.txt
intron_retention_utils.egg-info/dependency_links.txt
intron_retention_utils.egg-info/entry_points.txt
intron_retention_utils.egg-info/top_level.txt