Metadata-Version: 1.1
Name: intron-retention-utils
Version: 0.5.1
Summary: Python tools for extracting intron retention events
Home-page: https://github.com/friend1ws/intron_retention_utils
Author: Yuichi Shiraishi
Author-email: friend1ws@gamil.com
License: GPLv3
Platform: UNKNOWN
Classifier: Development Status :: 3 - Alpha
Classifier: Intended Audience :: Science/Research
Classifier: License :: OSI Approved :: GNU General Public License v3 (GPLv3)
Classifier: Operating System :: Unix
Classifier: Programming Language :: Python :: 2.7
Classifier: Topic :: Scientific/Engineering :: Bio-Informatics
